Workbook

Sheet 01_Cover
A1: Visa Institutional Equity Research Model V2
A2: FIG / Payments Coverage Model
A4: Company | B4: Visa Inc.
A5: Ticker | B5: NYSE: V
A6: Sector | B6: Financial Institutions / Payments
A7: Purpose | B7: Institutional-style equity research, valuation, and KPI model
A8: Primary Outputs | B8: DCF, trading comps, precedents, SOTP, scenarios, KPI dashboard
A9: Status | B9: V2 model scaffold; historical data and market data should be refreshed before use
A12: Color Code
A13: Yellow | B13: Hardcoded input
A14: Blue | B14: Formula
A15: Green | B15: Output

Sheet 02_Sources
A1: Sources
A2: All major figures should be traceable to filings, transcripts, or public market data.
A4: Source Type | B4: Document | C4: Date | D4: Metric / Section | E4: Reference | F4: Notes
A5: Company Filing | B5: Visa 10-K | C5: TBD | D5: Historical financials / KPIs | E5: TBD | F5: Add filing section or page
A6: Company Filing | B6: Visa 10-Q | C6: TBD | D6: Quarterly update | E6: TBD | F6: Add filing section or page
A7: Transcript | B7: Visa earnings call | C7: TBD | D7: Management commentary | E7: TBD | F7: Add transcript source
A8: Peer Filing | B8: Mastercard 10-K | C8: TBD | D8: Peer comparison | E8: TBD | F8: Add filing section or page
A9: Market Data | B9: Public market data | C9: TBD | D9: Share price / multiples | E9: TBD | F9: Refresh before use

Sheet 03_Setup_Control
A1: Setup and Control
A2: Central assumptions for valuation and scenarios.
A4: Assumption | B4: Base | C4: Bear | D4: Bull | E4: Notes
A5: Current Share Price | E5: Input latest price
A6: Diluted Shares | E6: Input latest diluted shares
A7: Net Cash / (Debt) | E7: Cash less debt
A8: WACC | B8: 0.085 | C8: 0.095 | D8: 0.075 | E8: Discount rate
A9: Terminal Growth Rate | B9: 0.035 | C9: 0.025 | D9: 0.045 | E9: Perpetuity growth
A10: Exit EBITDA Multiple | B10: 20 | C10: 16 | D10: 24 | E10: Terminal value cross-check
A11: Target P/E Multiple | B11: 30 | C11: 24 | D11: 35 | E11: Forward EPS multiple

Sheet 04_Historical_Financials
A1: Historical Financials
A2: Input reported historical financials and forecast core line items.
A4: $ in millions, except per-share data | B4: FY2021A | C4: FY2022A | D4: FY2023A | E4: FY2024A | F4: FY2025A | G4: FY2026E | H4: FY2027E | I4: FY2028E
A5: Net Revenue
A6: YoY Revenue Growth | C6: =C5/B5-1 | D6: =D5/C5-1 | E6: =E5/D5-1 | F6: =F5/E5-1 | G6: =G5/F5-1 | H6: =H5/G5-1 | I6: =I5/H5-1
A7: Operating Expenses
A8: Operating Income | B8: =B5-B7 | C8: =C5-C7 | D8: =D5-D7 | E8: =E5-E7 | F8: =F5-F7 | G8: =G5-G7 | H8: =H5-H7 | I8: =I5-I7
A9: Operating Margin | B9: =B8/B5 | C9: =C8/C5 | D9: =D8/D5 | E9: =E8/E5 | F9: =F8/F5 | G9: =G8/G5 | H9: =H8/H5 | I9: =I8/I5
A10: Net Income
A11: Diluted EPS
A12: Operating Cash Flow
A13: Capital Expenditures
A14: Free Cash Flow | B14: =B12-B13 | C14: =C12-C13 | D14: =D12-D13 | E14: =E12-E13 | F14: =F12-F13 | G14: =G12-G13 | H14: =H12-H13 | I14: =I12-I13
A15: Diluted Shares

Sheet 05_KPI_History
A1: Payments KPI History
A2: Operating KPIs specific to networks and payments.
A4: KPI | B4: FY2021A | C4: FY2022A | D4: FY2023A | E4: FY2024A | F4: FY2025A | G4: FY2026E | H4: FY2027E | I4: FY2028E | J4: Why It Matters
A5: Payments Volume | J5: Primary scale driver
A6: Processed Transactions | J6: Data processing driver
A7: Cross-Border Volume | J7: High-yield international driver
A8: Credentials | J8: Network reach
A9: Acceptance Locations | J9: Merchant acceptance moat
A10: Gross Revenue Yield | J10: Pre-incentive monetization
A11: Net Revenue Yield | J11: Post-incentive monetization
A12: Client Incentives / Gross Revenue | J12: Pricing pressure
A13: VAS Revenue | J13: Services growth driver
A14: VAS % of Net Revenue | J14: Mix shift indicator

Sheet 06_Revenue_Build
A1: Revenue Build
A2: Driver-based revenue forecast.
A4: $ in millions | B4: FY2021A | C4: FY2022A | D4: FY2023A | E4: FY2024A | F4: FY2025A | G4: FY2026E | H4: FY2027E | I4: FY2028E
A5: Service Revenue
A6: Data Processing Revenue
A7: International Transaction Revenue
A8: Other Revenue
A9: Gross Revenue | B9: =SUM(B5:B8) | C9: =SUM(C5:C8) | D9: =SUM(D5:D8) | E9: =SUM(E5:E8) | F9: =SUM(F5:F8) | G9: =SUM(G5:G8) | H9: =SUM(H5:H8) | I9: =SUM(I5:I8)
A10: Client Incentives
A11: Net Revenue | B11: =B9-B10 | C11: =C9-C10 | D11: =D9-D10 | E11: =E9-E10 | F11: =F9-F10 | G11: =G9-G10 | H11: =H9-H10 | I11: =I9-I10
A12: Net Revenue Growth | C12: =C11/B11-1 | D12: =D11/C11-1 | E12: =E11/D11-1 | F12: =F11/E11-1 | G12: =G11/F11-1 | H12: =H11/G11-1 | I12: =I11/H11-1

Sheet 07_Client_Incentives
A1: Client Incentives
A2: Analyze partner economics and take-rate pressure.
A4: Metric | B4: FY2021A | C4: FY2022A | D4: FY2023A | E4: FY2024A | F4: FY2025A | G4: FY2026E | H4: FY2027E | I4: FY2028E
A5: Gross Revenue | B5: ='06_Revenue_Build'!B9 | C5: ='06_Revenue_Build'!C9 | D5: ='06_Revenue_Build'!D9 | E5: ='06_Revenue_Build'!E9 | F5: ='06_Revenue_Build'!F9 | G5: ='06_Revenue_Build'!G9 | H5: ='06_Revenue_Build'!H9 | I5: ='06_Revenue_Build'!I9
A6: Client Incentives | B6: ='06_Revenue_Build'!B10 | C6: ='06_Revenue_Build'!C10 | D6: ='06_Revenue_Build'!D10 | E6: ='06_Revenue_Build'!E10 | F6: ='06_Revenue_Build'!F10 | G6: ='06_Revenue_Build'!G10 | H6: ='06_Revenue_Build'!H10 | I6: ='06_Revenue_Build'!I10
A7: Net Revenue | B7: ='06_Revenue_Build'!B11 | C7: ='06_Revenue_Build'!C11 | D7: ='06_Revenue_Build'!D11 | E7: ='06_Revenue_Build'!E11 | F7: ='06_Revenue_Build'!F11 | G7: ='06_Revenue_Build'!G11 | H7: ='06_Revenue_Build'!H11 | I7: ='06_Revenue_Build'!I11
A8: Client Incentives / Gross Revenue | B8: =B6/B5 | C8: =C6/C5 | D8: =D6/D5 | E8: =E6/E5 | F8: =F6/F5 | G8: =G6/G5 | H8: =H6/H5 | I8: =I6/I5
A9: Incremental Incentive Ratio | C9: =(C6-B6)/(C5-B5) | D9: =(D6-C6)/(D5-C5) | E9: =(E6-D6)/(E5-D5) | F9: =(F6-E6)/(F5-E5) | G9: =(G6-F6)/(G5-F5) | H9: =(H6-G6)/(H5-G5) | I9: =(I6-H6)/(I5-H5)

Sheet 08_VAS_Model
A1: Value-Added Services Model
A2: Analyze Visa's services growth runway.
A4: Metric | B4: FY2021A | C4: FY2022A | D4: FY2023A | E4: FY2024A | F4: FY2025A | G4: FY2026E | H4: FY2027E | I4: FY2028E
A5: VAS Revenue
A6: VAS Growth | C6: =C5/B5-1 | D6: =D5/C5-1 | E6: =E5/D5-1 | F6: =F5/E5-1 | G6: =G5/F5-1 | H6: =H5/G5-1 | I6: =I5/H5-1
A7: Net Revenue | B7: ='06_Revenue_Build'!B11 | C7: ='06_Revenue_Build'!C11 | D7: ='06_Revenue_Build'!D11 | E7: ='06_Revenue_Build'!E11 | F7: ='06_Revenue_Build'!F11 | G7: ='06_Revenue_Build'!G11 | H7: ='06_Revenue_Build'!H11 | I7: ='06_Revenue_Build'!I11
A8: VAS % of Net Revenue | B8: =B5/B7 | C8: =C5/C7 | D8: =D5/D7 | E8: =E5/E7 | F8: =F5/F7 | G8: =G5/G7 | H8: =H5/H7 | I8: =I5/I7
A9: Illustrative VAS Margin
A10: Illustrative VAS EBIT | B10: =B5*B9 | C10: =C5*C9 | D10: =D5*D9 | E10: =E5*E9 | F10: =F5*F9 | G10: =G5*G9 | H10: =H5*H9 | I10: =I5*I9

Sheet 09_Cross_Border_Model
A1: Cross-Border Model
A2: High-yield international revenue sensitivity.
A4: Metric | B4: FY2021A | C4: FY2022A | D4: FY2023A | E4: FY2024A | F4: FY2025A | G4: FY2026E | H4: FY2027E | I4: FY2028E
A5: Cross-Border Volume
A6: Cross-Border Volume Growth | C6: =C5/B5-1 | D6: =D5/C5-1 | E6: =E5/D5-1 | F6: =F5/E5-1 | G6: =G5/F5-1 | H6: =H5/G5-1 | I6: =I5/H5-1
A7: International Transaction Revenue
A8: International Revenue Growth | C8: =C7/B7-1 | D8: =D7/C7-1 | E8: =E7/D7-1 | F8: =F7/E7-1 | G8: =G7/F7-1 | H8: =H7/G7-1 | I8: =I7/H7-1
A9: International Revenue Yield | B9: =B7/B5 | C9: =C7/C5 | D9: =D7/D5 | E9: =E7/E5 | F9: =F7/F5 | G9: =G7/G5 | H9: =H7/H5 | I9: =I7/I5

Sheet 10_Operating_Expense_Build
A1: Operating Expense Build
A2: Forecast expenses and operating leverage.
A4: $ in millions | B4: FY2021A | C4: FY2022A | D4: FY2023A | E4: FY2024A | F4: FY2025A | G4: FY2026E | H4: FY2027E | I4: FY2028E
A5: Net Revenue | B5: ='06_Revenue_Build'!B11 | C5: ='06_Revenue_Build'!C11 | D5: ='06_Revenue_Build'!D11 | E5: ='06_Revenue_Build'!E11 | F5: ='06_Revenue_Build'!F11 | G5: ='06_Revenue_Build'!G11 | H5: ='06_Revenue_Build'!H11 | I5: ='06_Revenue_Build'!I11
A6: Personnel
A7: Marketing
A8: Network and Processing
A9: Professional Fees
A10: G&A / Other
A11: Total Operating Expenses | B11: =SUM(B6:B10) | C11: =SUM(C6:C10) | D11: =SUM(D6:D10) | E11: =SUM(E6:E10) | F11: =SUM(F6:F10) | G11: =SUM(G6:G10) | H11: =SUM(H6:H10) | I11: =SUM(I6:I10)
A12: Operating Income | B12: =B5-B11 | C12: =C5-C11 | D12: =D5-D11 | E12: =E5-E11 | F12: =F5-F11 | G12: =G5-G11 | H12: =H5-H11 | I12: =I5-I11
A13: Operating Margin | B13: =B12/B5 | C13: =C12/C5 | D13: =D12/D5 | E13: =E12/E5 | F13: =F12/F5 | G13: =G12/G5 | H13: =H12/H5 | I13: =I12/I5

Sheet 11_Margin_Walk
A1: Operating Margin Walk
A2: Bridge current margin to forecast margin.
A4: Driver | B4: Margin Impact | C4: Commentary
A5: FY2025 Operating Margin | C5: Starting point
A6: Volume Growth / Scale | C6: Operating leverage
A7: VAS Mix | C7: Services contribution
A8: Client Incentives | C8: Partner economics pressure
A9: Technology Investment | C9: Product and security investment
A10: Regulatory / Litigation | C10: Legal and compliance burden
A11: FY2028E Operating Margin | B11: =SUM(B5:B10) | C11: Ending margin

Sheet 12_Tax_DA_Capex_NWC
A1: Tax, D&A, Capex, and Working Capital
A2: Core free cash flow forecast assumptions.
A4: Metric | B4: FY2021A | C4: FY2022A | D4: FY2023A | E4: FY2024A | F4: FY2025A | G4: FY2026E | H4: FY2027E | I4: FY2028E
A5: Operating Income | B5: ='10_Operating_Expense_Build'!B12 | C5: ='10_Operating_Expense_Build'!C12 | D5: ='10_Operating_Expense_Build'!D12 | E5: ='10_Operating_Expense_Build'!E12 | F5: ='10_Operating_Expense_Build'!F12 | G5: ='10_Operating_Expense_Build'!G12 | H5: ='10_Operating_Expense_Build'!H12 | I5: ='10_Operating_Expense_Build'!I12
A6: Tax Rate
A7: NOPAT | B7: =B5*(1-B6) | C7: =C5*(1-C6) | D7: =D5*(1-D6) | E7: =E5*(1-E6) | F7: =F5*(1-F6) | G7: =G5*(1-G6) | H7: =H5*(1-H6) | I7: =I5*(1-I6)
A8: D&A
A9: D&A % Revenue | B9: =B8/'06_Revenue_Build'!B11 | C9: =C8/'06_Revenue_Build'!C11 | D9: =D8/'06_Revenue_Build'!D11 | E9: =E8/'06_Revenue_Build'!E11 | F9: =F8/'06_Revenue_Build'!F11 | G9: =G8/'06_Revenue_Build'!G11 | H9: =H8/'06_Revenue_Build'!H11 | I9: =I8/'06_Revenue_Build'!I11
A10: Capex
A11: Capex % Revenue | B11: =B10/'06_Revenue_Build'!B11 | C11: =C10/'06_Revenue_Build'!C11 | D11: =D10/'06_Revenue_Build'!D11 | E11: =E10/'06_Revenue_Build'!E11 | F11: =F10/'06_Revenue_Build'!F11 | G11: =G10/'06_Revenue_Build'!G11 | H11: =H10/'06_Revenue_Build'!H11 | I11: =I10/'06_Revenue_Build'!I11
A12: Change in NWC
A13: NWC % Revenue | B13: =B12/'06_Revenue_Build'!B11 | C13: =C12/'06_Revenue_Build'!C11 | D13: =D12/'06_Revenue_Build'!D11 | E13: =E12/'06_Revenue_Build'!E11 | F13: =F12/'06_Revenue_Build'!F11 | G13: =G12/'06_Revenue_Build'!G11 | H13: =H12/'06_Revenue_Build'!H11 | I13: =I12/'06_Revenue_Build'!I11

Sheet 13_Free_Cash_Flow
A1: Unlevered Free Cash Flow
A2: DCF cash flow build.
A4: $ in millions | B4: FY2021A | C4: FY2022A | D4: FY2023A | E4: FY2024A | F4: FY2025A | G4: FY2026E | H4: FY2027E | I4: FY2028E
A5: NOPAT | B5: ='12_Tax_DA_Capex_NWC'!B7 | C5: ='12_Tax_DA_Capex_NWC'!C7 | D5: ='12_Tax_DA_Capex_NWC'!D7 | E5: ='12_Tax_DA_Capex_NWC'!E7 | F5: ='12_Tax_DA_Capex_NWC'!F7 | G5: ='12_Tax_DA_Capex_NWC'!G7 | H5: ='12_Tax_DA_Capex_NWC'!H7 | I5: ='12_Tax_DA_Capex_NWC'!I7
A6: D&A | B6: ='12_Tax_DA_Capex_NWC'!B8 | C6: ='12_Tax_DA_Capex_NWC'!C8 | D6: ='12_Tax_DA_Capex_NWC'!D8 | E6: ='12_Tax_DA_Capex_NWC'!E8 | F6: ='12_Tax_DA_Capex_NWC'!F8 | G6: ='12_Tax_DA_Capex_NWC'!G8 | H6: ='12_Tax_DA_Capex_NWC'!H8 | I6: ='12_Tax_DA_Capex_NWC'!I8
A7: Capital Expenditures | B7: ='12_Tax_DA_Capex_NWC'!B10 | C7: ='12_Tax_DA_Capex_NWC'!C10 | D7: ='12_Tax_DA_Capex_NWC'!D10 | E7: ='12_Tax_DA_Capex_NWC'!E10 | F7: ='12_Tax_DA_Capex_NWC'!F10 | G7: ='12_Tax_DA_Capex_NWC'!G10 | H7: ='12_Tax_DA_Capex_NWC'!H10 | I7: ='12_Tax_DA_Capex_NWC'!I10
A8: Change in NWC | B8: ='12_Tax_DA_Capex_NWC'!B12 | C8: ='12_Tax_DA_Capex_NWC'!C12 | D8: ='12_Tax_DA_Capex_NWC'!D12 | E8: ='12_Tax_DA_Capex_NWC'!E12 | F8: ='12_Tax_DA_Capex_NWC'!F12 | G8: ='12_Tax_DA_Capex_NWC'!G12 | H8: ='12_Tax_DA_Capex_NWC'!H12 | I8: ='12_Tax_DA_Capex_NWC'!I12
A9: Unlevered FCF | B9: =B5+B6-B7-B8 | C9: =C5+C6-C7-C8 | D9: =D5+D6-D7-D8 | E9: =E5+E6-E7-E8 | F9: =F5+F6-F7-F8 | G9: =G5+G6-G7-G8 | H9: =H5+H6-H7-H8 | I9: =I5+I6-I7-I8
A10: FCF Margin | B10: =B9/'06_Revenue_Build'!B11 | C10: =C9/'06_Revenue_Build'!C11 | D10: =D9/'06_Revenue_Build'!D11 | E10: =E9/'06_Revenue_Build'!E11 | F10: =F9/'06_Revenue_Build'!F11 | G10: =G9/'06_Revenue_Build'!G11 | H10: =H9/'06_Revenue_Build'!H11 | I10: =I9/'06_Revenue_Build'!I11
A11: FCF Growth | C11: =C9/B9-1 | D11: =D9/C9-1 | E11: =E9/D9-1 | F11: =F9/E9-1 | G11: =G9/F9-1 | H11: =H9/G9-1 | I11: =I9/H9-1

Sheet 14_Share_Count_Buybacks
A1: Share Count and Buybacks
A2: Model EPS accretion from capital return.
A4: Metric | B4: FY2021A | C4: FY2022A | D4: FY2023A | E4: FY2024A | F4: FY2025A | G4: FY2026E | H4: FY2027E | I4: FY2028E
A5: Beginning Diluted Shares
A6: Repurchase Dollars
A7: Average Repurchase Price
A8: Shares Retired | B8: =B6/B7 | C8: =C6/C7 | D8: =D6/D7 | E8: =E6/E7 | F8: =F6/F7 | G8: =G6/G7 | H8: =H6/H7 | I8: =I6/I7
A9: SBC / Other
A10: Ending Diluted Shares | B10: =B5-B8+B9 | C10: =C5-C8+C9 | D10: =D5-D8+D9 | E10: =E5-E8+E9 | F10: =F5-F8+F9 | G10: =G5-G8+G9 | H10: =H5-H8+H9 | I10: =I5-I8+I9
A11: Net Income | B11: ='04_Historical_Financials'!B10 | C11: ='04_Historical_Financials'!C10 | D11: ='04_Historical_Financials'!D10 | E11: ='04_Historical_Financials'!E10 | F11: ='04_Historical_Financials'!F10 | G11: ='04_Historical_Financials'!G10 | H11: ='04_Historical_Financials'!H10 | I11: ='04_Historical_Financials'!I10
A12: Diluted EPS | B12: =B11/B10 | C12: =C11/C10 | D12: =D11/D10 | E12: =E11/E10 | F12: =F11/F10 | G12: =G11/G10 | H12: =H11/H10 | I12: =I11/I10

Sheet 15_DCF
A1: DCF Valuation
A2: Intrinsic valuation using unlevered free cash flow.
A4: $ in millions | B4: FY2021A | C4: FY2022A | D4: FY2023A | E4: FY2024A | F4: FY2025A | G4: FY2026E | H4: FY2027E | I4: FY2028E
A5: Unlevered FCF | B5: ='13_Free_Cash_Flow'!B9 | C5: ='13_Free_Cash_Flow'!C9 | D5: ='13_Free_Cash_Flow'!D9 | E5: ='13_Free_Cash_Flow'!E9 | F5: ='13_Free_Cash_Flow'!F9 | G5: ='13_Free_Cash_Flow'!G9 | H5: ='13_Free_Cash_Flow'!H9 | I5: ='13_Free_Cash_Flow'!I9
A6: Discount Period | B6: 1 | C6: 2 | D6: 3 | E6: 4 | F6: 5 | G6: 6 | H6: 7 | I6: 8
A7: Discount Factor | B7: =1/(1+'03_Setup_Control'!B8)^B6 | C7: =1/(1+'03_Setup_Control'!B8)^C6 | D7: =1/(1+'03_Setup_Control'!B8)^D6 | E7: =1/(1+'03_Setup_Control'!B8)^E6 | F7: =1/(1+'03_Setup_Control'!B8)^F6 | G7: =1/(1+'03_Setup_Control'!B8)^G6 | H7: =1/(1+'03_Setup_Control'!B8)^H6 | I7: =1/(1+'03_Setup_Control'!B8)^I6
A8: PV of FCF | B8: =B5*B7 | C8: =C5*C7 | D8: =D5*D7 | E8: =E5*E7 | F8: =F5*F7 | G8: =G5*G7 | H8: =H5*H7 | I8: =I5*I7
A12: PV of Explicit FCF | B12: =SUM(B8:I8)
A13: Terminal FCF | B13: =I5*(1+'03_Setup_Control'!B9)
A14: Terminal Value | B14: =B13/('03_Setup_Control'!B8-'03_Setup_Control'!B9)
A15: PV of Terminal Value | B15: =B14*I7
A16: Enterprise Value | B16: =B12+B15
A17: Net Cash / (Debt) | B17: ='03_Setup_Control'!B7
A18: Equity Value | B18: =B16+B17
A19: Diluted Shares | B19: ='03_Setup_Control'!B6
A20: Implied DCF Value / Share | B20: =B18/B19

Sheet 16_Trading_Comps
A1: Trading Comparable Company Analysis
A2: Benchmark Visa against payments peers.
A4: Company | B4: Ticker | C4: Peer Group | D4: Market Cap | E4: EV | F4: Revenue Growth | G4: EBITDA Margin | H4: P/E | I4: EV/EBITDA | J4: FCF Yield | K4: Notes
A5: Visa | B5: V | C5: Network
A6: Mastercard | B6: MA | C6: Network
A7: American Express | B7: AXP | C7: Closed-loop
A8: Fiserv | B8: FI | C8: Processor
A9: Global Payments | B9: GPN | C9: Processor
A10: Shift4 | B10: FOUR | C10: Acquirer / PSP
A11: Adyen | B11: ADYEN | C11: Acquirer / PSP
A12: PayPal | B12: PYPL | C12: Wallet / Fintech
A13: Block | B13: XYZ | C13: Wallet / Fintech
A14: FIS | B14: FIS | C14: Infrastructure

Sheet 17_Precedent_Transactions
A1: Precedent Transaction Analysis
A2: Payments M&A valuation context.
A4: Date | B4: Acquirer | C4: Target | D4: Category | E4: Transaction Value | F4: Revenue | G4: EBITDA | H4: EV/Revenue | I4: EV/EBITDA | J4: Strategic Rationale | K4: Relevance to Visa
H5: =E5/F5 | I5: =E5/G5
H6: =E6/F6 | I6: =E6/G6
H7: =E7/F7 | I7: =E7/G7
H8: =E8/F8 | I8: =E8/G8
H9: =E9/F9 | I9: =E9/G9
H10: =E10/F10 | I10: =E10/G10
H11: =E11/F11 | I11: =E11/G11
H12: =E12/F12 | I12: =E12/G12
H13: =E13/F13 | I13: =E13/G13
H14: =E14/F14 | I14: =E14/G14

Sheet 18_SOTP
A1: Sum-of-the-Parts Valuation
A2: Separate core network, VAS, and money movement value pools.
A4: Segment | B4: Metric | C4: Metric Value | D4: Multiple | E4: Implied Value | F4: Rationale
A5: Core Consumer Payments Network | E5: =C5*D5
A6: Commercial / B2B Payments | E6: =C6*D6
A7: Value-Added Services | E7: =C7*D7
A8: Visa Direct / Money Movement | E8: =C8*D8
A9: Net Cash / Other | E9: =C9*D9
D12: Total SOTP Equity Value | E12: =SUM(E5:E9)

Sheet 19_Scenario_Manager
A1: Scenario Manager
A2: Driver-based severe downside, bear, base, and bull cases.
A4: Driver | B4: Severe Downside | C4: Bear | D4: Base | E4: Bull
A5: Revenue CAGR
A6: Operating Margin
A7: Client Incentives / Gross Revenue
A8: VAS Growth
A9: Cross-Border Growth
A10: Terminal P/E
A11: DCF Value / Share
A12: Comps Value / Share
A13: Scenario Target Price | B13: =AVERAGE(B11:B12) | C13: =AVERAGE(C11:C12) | D13: =AVERAGE(D11:D12) | E13: =AVERAGE(E11:E12)

Sheet 20_Sensitivity_Tables
A1: Sensitivity Tables
A2: DCF and valuation sensitivity outputs.
A4: DCF Sensitivity: WACC vs Terminal Growth
B5: 0.075 | C5: 0.08 | D5: 0.085 | E5: 0.09 | F5: 0.095
A6: 0.025 | B6: Link to DCF | C6: Link to DCF | D6: Link to DCF | E6: Link to DCF | F6: Link to DCF
A7: 0.03 | B7: Link to DCF | C7: Link to DCF | D7: Link to DCF | E7: Link to DCF | F7: Link to DCF
A8: 0.035 | B8: Link to DCF | C8: Link to DCF | D8: Link to DCF | E8: Link to DCF | F8: Link to DCF
A9: 0.04 | B9: Link to DCF | C9: Link to DCF | D9: Link to DCF | E9: Link to DCF | F9: Link to DCF
A10: 0.045 | B10: Link to DCF | C10: Link to DCF | D10: Link to DCF | E10: Link to DCF | F10: Link to DCF

Sheet 21_Consensus_Bridge
A1: Consensus Bridge
A2: Compare project estimates with consensus expectations.
A4: Metric | B4: FY2026E Consensus | C4: FY2026E Project | D4: Variance | E4: FY2027E Consensus | F4: FY2027E Project | G4: Variance | H4: Interpretation
A5: Net Revenue | D5: =C5-B5 | G5: =F5-E5
A6: Operating Margin | D6: =C6-B6 | G6: =F6-E6
A7: EPS | D7: =C7-B7 | G7: =F7-E7
A8: FCF | D8: =C8-B8 | G8: =F8-E8
A9: Buybacks | D9: =C9-B9 | G9: =F9-E9
A10: Target P/E | D10: =C10-B10 | G10: =F10-E10

Sheet 22_Output_Dashboard
A1: Output Dashboard
A2: Recruiter-friendly model summary.
A4: Recommendation | B4: Outperform / Base Case Positive
A5: Primary Valuation Method | B5: DCF + Forward P/E + Comps
A6: DCF Value / Share | B6: ='15_DCF'!B20
A7: Base Scenario Target | B7: ='19_Scenario_Manager'!D13
A8: Bear Scenario Target | B8: ='19_Scenario_Manager'!C13
A9: Bull Scenario Target | B9: ='19_Scenario_Manager'!E13
A10: Key Debate | B10: Take-rate durability vs regulatory and alternative-rail pressure
A11: Variant Perception | B11: VAS, tokenization, risk/fraud, and money movement extend network relevance

Sheet 23_Charts
A1: Charts
A2: Placeholder sheet for report-ready chart outputs.
A4: Revenue and margin trend
A5: Payments volume and processed transactions
A6: Cross-border volume
A7: Client incentives as % of gross revenue
A8: VAS revenue mix
A9: Peer valuation comparison
A10: DCF sensitivity
A11: Scenario output matrix
A12: Football field valuation

Sheet 24_Model_Checks
A1: Model Checks
A2: Quality-control checks for model integrity.
A4: Check | B4: Logic | C4: Status
A5: Revenue Build Check | B5: Gross Revenue - Client Incentives = Net Revenue | C5: =IF(ABS('06_Revenue_Build'!I9-'06_Revenue_Build'!I10-'06_Revenue_Build'!I11)<1,"OK","ERROR")
A6: FCF Check | B6: NOPAT + D&A - Capex - NWC = UFCF | C6: =IF(ABS('13_Free_Cash_Flow'!I5+'13_Free_Cash_Flow'!I6-'13_Free_Cash_Flow'!I7-'13_Free_Cash_Flow'!I8-'13_Free_Cash_Flow'!I9)<1,"OK","ERROR")
A7: DCF Check | B7: Equity Value / Shares = Value per Share | C7: =IFERROR(IF(ABS('15_DCF'!B18/'15_DCF'!B19-'15_DCF'!B20)<0.01,"OK","ERROR"),"CHECK INPUTS")

Sheet 25_Print_Package
A1: Print Package
A2: Sections to print/export for appendix.
A4: Output Dashboard
A5: DCF
A6: Trading Comps
A7: Precedents
A8: SOTP
A9: Scenarios
A10: Sensitivities
A11: Model Checks
